recombee_api_client/__init__.py
recombee_api_client/api_client.py
recombee_api_client/exceptions.py
recombee_api_client/api_requests/__init__.py
recombee_api_client/api_requests/add_bookmark.py
recombee_api_client/api_requests/add_cart_addition.py
recombee_api_client/api_requests/add_detail_view.py
recombee_api_client/api_requests/add_item.py
recombee_api_client/api_requests/add_item_property.py
recombee_api_client/api_requests/add_manual_reql_segment.py
recombee_api_client/api_requests/add_purchase.py
recombee_api_client/api_requests/add_rating.py
recombee_api_client/api_requests/add_search_synonym.py
recombee_api_client/api_requests/add_series.py
recombee_api_client/api_requests/add_user.py
recombee_api_client/api_requests/add_user_property.py
recombee_api_client/api_requests/batch.py
recombee_api_client/api_requests/composite_recommendation.py
recombee_api_client/api_requests/create_auto_reql_segmentation.py
recombee_api_client/api_requests/create_manual_reql_segmentation.py
recombee_api_client/api_requests/create_property_based_segmentation.py
recombee_api_client/api_requests/delete_all_search_synonyms.py
recombee_api_client/api_requests/delete_bookmark.py
recombee_api_client/api_requests/delete_cart_addition.py
recombee_api_client/api_requests/delete_detail_view.py
recombee_api_client/api_requests/delete_item.py
recombee_api_client/api_requests/delete_item_property.py
recombee_api_client/api_requests/delete_manual_reql_segment.py
recombee_api_client/api_requests/delete_more_items.py
recombee_api_client/api_requests/delete_purchase.py
recombee_api_client/api_requests/delete_rating.py
recombee_api_client/api_requests/delete_search_synonym.py
recombee_api_client/api_requests/delete_segmentation.py
recombee_api_client/api_requests/delete_series.py
recombee_api_client/api_requests/delete_user.py
recombee_api_client/api_requests/delete_user_property.py
recombee_api_client/api_requests/delete_view_portion.py
recombee_api_client/api_requests/get_item_property_info.py
recombee_api_client-6.0.0.dist-info/licenses/LICENSE
recombee_api_client-6.0.0.dist-info/METADATA
recombee_api_client-6.0.0.dist-info/WHEEL
recombee_api_client-6.0.0.dist-info/top_level.txt
recombee_api_client-6.0.0.dist-info/RECORD
